Workbook

Sheet FRAGILITY DASHBOARD
A1: REAL-TIME FRAGILITY INTELLIGENCE DASHBOARD
A2: LAST UPDATE: | B2: =NOW() -> 46069.551 | D2: YOUR AGE: | E2: =ROUND((NOW()-Settings!B2)/365.25,4) -> 31.1281 | G2: LOCATION: | H2: =Settings!B3 -> Chennai, India
A4: MULTI-SCALE FRAGILITY MATRIX
A5: SCALE | B5: SELF | C5: FAMILY | D5: LOCAL | E5: NATIONAL | F5: CIVILIZATIONAL | G5: PLANETARY | H5: AVERAGE
A6: Physics | B6: =Physics!B4 -> 80 | C6: =Physics!C4 -> 10 | D6: =Physics!D4 -> 8 | E6: =Physics!E4 -> Grid dependency, no bunker, no Faraday cage | F6: =Physics!F4 -> Define action | G6: =Physics!G4 -> NOT STARTED
A7: Biology | B7: =Biology!B4 -> 80 | C7: =Biology!C4 -> 10 | D7: =Biology!D4 -> 8 | E7: =Biology!E4 -> Sedentary lifestyle, poor sleep, inflammation | F7: =Biology!F4 -> Define action | G7: =Biology!G4 -> NOT STARTED
A8: Ecology | B8: =Ecology!B4 -> 80 | C8: =Ecology!C4 -> 10 | D8: =Ecology!D4 -> 8 | E8: =Ecology!E4 -> Low status, visible wealth, no force capability | F8: =Ecology!F4 -> Define action | G8: =Ecology!G4 -> NOT STARTED
A9: Politics | B9: =Politics!B4 -> 80 | C9: =Politics!C4 -> 10 | D9: =Politics!D4 -> 8 | E9: =Politics!E4 -> Traceable assets, legal exposure, single jurisdiction | F9: =Politics!F4 -> Define action | G9: =Politics!G4 -> NOT STARTED
A10: Finance | B10: =Finance!B4 -> 80 | C10: =Finance!C4 -> 10 | D10: =Finance!D4 -> 8 | E10: =Finance!E4 -> Debt burden, fiat savings, W2 income only | F10: =Finance!F4 -> Define action | G10: =Finance!G4 -> NOT STARTED
A11: Nurture | B11: =Nurture!B4 -> 80 | C11: =Nurture!C4 -> 10 | D11: =Nurture!D4 -> 8 | E11: =Nurture!E4 -> Reputation risk, cancel culture, mimetic contagion | F11: =Nurture!F4 -> Define action | G11: =Nurture!G4 -> NOT STARTED
A12: TOTAL FRAGILITY | B12: =AVERAGE(B6:B11) -> 80 | C12: =AVERAGE(B6:C11) -> 45 | D12: =AVERAGE(B6:D11) -> 32.666667 | E12: =AVERAGE(B6:E11) -> 32.666667 | F12: =AVERAGE(B6:F11) -> 32.666667 | G12: =AVERAGE(B6:G11) -> 32.666667 | H12: =AVERAGE(B6:H11) -> 32.666667
A14: DOMAIN ANALYZER
A15: SELECT DOMAIN: | B15: Physics
A16: SELECTED DOMAIN METRICS:
A17: Scale | B17: Fragility | C17: Stakes | D17: Risk | E17: Vulnerabilities | F17: Top Priority Action | G17: Status
A18: SELF | B18: =INDIRECT($B$15&"!B4") -> 80 | C18: =INDIRECT($B$15&"!C4") -> 10 | D18: =INDIRECT($B$15&"!D4") -> 8 | E18: =INDIRECT($B$15&"!E4") -> Grid dependency, no bunker, no Faraday cage | F18: =INDIRECT($B$15&"!F4") -> Define action | G18: =INDIRECT($B$15&"!G4") -> NOT STARTED
A19: FAMILY | B19: =INDIRECT($B$15&"!B5") -> 63 | C19: =INDIRECT($B$15&"!C5") -> 9 | D19: =INDIRECT($B$15&"!D5") -> 7 | E19: =INDIRECT($B$15&"!E5") -> Family on grid, urban living, no escape plan | F19: =INDIRECT($B$15&"!F5") -> Define action | G19: =INDIRECT($B$15&"!G5") -> NOT STARTED
A20: LOCAL | B20: =INDIRECT($B$15&"!B6") -> 42 | C20: =INDIRECT($B$15&"!C6") -> 7 | D20: =INDIRECT($B$15&"!D6") -> 6 | E20: =INDIRECT($B$15&"!E6") -> City grid vulnerable, transformer shortage | F20: =INDIRECT($B$15&"!F6") -> Define action | G20: =INDIRECT($B$15&"!G6") -> NOT STARTED
A21: NATIONAL | B21: =INDIRECT($B$15&"!B7") -> 56 | C21: =INDIRECT($B$15&"!C7") -> 8 | D21: =INDIRECT($B$15&"!D7") -> 7 | E21: =INDIRECT($B$15&"!E7") -> Grid interconnected, no hardening, political gridlock | F21: =INDIRECT($B$15&"!F7") -> Define action | G21: =INDIRECT($B$15&"!G7") -> NOT STARTED
A22: CIVILIZATIONAL | B22: =INDIRECT($B$15&"!B8") -> 48 | C22: =INDIRECT($B$15&"!C8") -> 6 | D22: =INDIRECT($B$15&"!D8") -> 8 | E22: =INDIRECT($B$15&"!E8") -> Tech dependency, satellite vulnerability, solar cycle peak | F22: =INDIRECT($B$15&"!F8") -> Define action | G22: =INDIRECT($B$15&"!G8") -> NOT STARTED
A23: PLANETARY | B23: =INDIRECT($B$15&"!B9") -> 45 | C23: =INDIRECT($B$15&"!C9") -> 5 | D23: =INDIRECT($B$15&"!D9") -> 9 | E23: =INDIRECT($B$15&"!E9") -> Solar cycle 25 peak, magnetosphere weakening, pole shift | F23: =INDIRECT($B$15&"!F9") -> Define action | G23: =INDIRECT($B$15&"!G9") -> NOT STARTED
A25: STRATEGIC OPERATIONAL MATRIX
A26: DOMAIN: | B26: =B15 -> Physics
A27: Type | B27: Relation | C27: Posture | D27: Strategy | E27: Status
A28: OVERT | B28: ALLIES | C28: OFFENSE | D28: =INDIRECT($B$15&"!B3") -> Fragility (0-100) | E28: ACTIVE
A29: OVERT | B29: ALLIES | C29: DEFENSE | D29: =INDIRECT($B$15&"!C3") -> Stakes (1-10) | E29: ACTIVE
A30: OVERT | B30: ENEMIES | C30: OFFENSE | D30: =INDIRECT($B$15&"!D3") -> Risk (1-10) | E30: ACTIVE
A31: OVERT | B31: ENEMIES | C31: DEFENSE | D31: =INDIRECT($B$15&"!E3") -> Vulnerabilities | E31: ACTIVE
A32: COVERT | B32: ALLIES | C32: OFFENSE | D32: =INDIRECT($B$15&"!B8") -> 48 | E32: ACTIVE
A33: COVERT | B33: ALLIES | C33: DEFENSE | D33: =INDIRECT($B$15&"!C8") -> 6 | E33: ACTIVE
A34: COVERT | B34: ENEMIES | C34: OFFENSE | D34: =INDIRECT($B$15&"!D8") -> 8 | E34: ACTIVE
A35: COVERT | B35: ENEMIES | C35: DEFENSE | D35: =INDIRECT($B$15&"!E8") -> Tech dependency, satellite vulnerability, solar cycle peak | E35: ACTIVE
A37: BARBELL STRATEGY MONITOR (90/10 DEFENSE/OFFENSE)
A38: Metric | B38: Target % | C38: Current % | D38: Variance | E38: Status
A39: Affairs (Defense) | B39: 90 | C39: =BarbellTracker!C3 -> 85 | D39: =C39-B39 -> -5 | E39: =IF(ABS(D39)<=5,"✓ BALANCED","⚠ ADJUST") -> ✓ BALANCED
A40: Interests (Offense) | B40: 10 | C40: =BarbellTracker!C4 -> 15 | D40: =C40-B40 -> 5 | E40: =IF(ABS(D40)<=5,"✓ BALANCED","⚠ ADJUST") -> ✓ BALANCED
A41: Time Allocation (hrs/week) | B41: 150 | C41: =BarbellTracker!C5 -> 145 | D41: =C41-B41 -> -5 | E41: =IF(ABS(D41)<=10,"✓ ON TRACK","⚠ ADJUST") -> ✓ ON TRACK

Sheet Settings
A1: SYSTEM SETTINGS & PERSONAL DATA
A2: Birth Date | B2: =DATE(1995,1,1) -> 34700
A3: Current Location | B3: Chennai, India
A4: Life Expectancy (years) | B4: 80
A6: FRAGILITY THRESHOLDS
A7: Critical (Red) | B7: 70
A8: Medium (Yellow) | B8: 40
A9: Low (Green) | B9: 20

Sheet Physics
A1: PHYSICS - Laws of Physics - Grid collapse, CMEs, disasters
A3: Scale | B3: Fragility (0-100) | C3: Stakes (1-10) | D3: Risk (1-10) | E3: Vulnerabilities | F3: Priority Action | G3: Status
A4: SELF | B4: =C4*D4 -> 80 | C4: 10 | D4: 8 | E4: Grid dependency, no bunker, no Faraday cage | F4: Define action | G4: NOT STARTED
A5: FAMILY | B5: =C5*D5 -> 63 | C5: 9 | D5: 7 | E5: Family on grid, urban living, no escape plan | F5: Define action | G5: NOT STARTED
A6: LOCAL | B6: =C6*D6 -> 42 | C6: 7 | D6: 6 | E6: City grid vulnerable, transformer shortage | F6: Define action | G6: NOT STARTED
A7: NATIONAL | B7: =C7*D7 -> 56 | C7: 8 | D7: 7 | E7: Grid interconnected, no hardening, political gridlock | F7: Define action | G7: NOT STARTED
A8: CIVILIZATIONAL | B8: =C8*D8 -> 48 | C8: 6 | D8: 8 | E8: Tech dependency, satellite vulnerability, solar cycle peak | F8: Define action | G8: NOT STARTED
A9: PLANETARY | B9: =C9*D9 -> 45 | C9: 5 | D9: 9 | E9: Solar cycle 25 peak, magnetosphere weakening, pole shift | F9: Define action | G9: NOT STARTED
A11: AFFAIRS (DEFENSE) - Hedge tail risks at this scale
A12: Scale | B12: Affair | C12: Stakes | D12: Time (hrs) | E12: Due Date | F12: Status | G12: Completion %
A13: Self
A14: Family
A15: Local
A16: National
A17: Civilizational
A18: Planetary
A20: INTERESTS (OFFENSE) - Asymmetric bets at this scale
A21: Scale | B21: Interest | C21: Asymmetry | D21: Upside | E21: Downside | F21: Status | G21: ROI
A22: Self
A23: Family
A24: Local
A25: National
A26: Civilizational
A27: Planetary
A30: STRATEGIC MATRIX (Overt/Covert × Ally/Enemy × Offense/Defense)
B31: ALLIES OFFENSE | C31: ALLIES DEFENSE | D31: ENEMIES OFFENSE | E31: ENEMIES DEFENSE
A32: OVERT | B32: Define strategy | C32: Define strategy | D32: Define strategy | E32: Define strategy
A33: COVERT | B33: Define strategy | C33: Define strategy | D33: Define strategy | E33: Define strategy

Sheet Biology
A1: BIOLOGY - Laws of Nature - Atrophy, disease, aging, entropy
A3: Scale | B3: Fragility (0-100) | C3: Stakes (1-10) | D3: Risk (1-10) | E3: Vulnerabilities | F3: Priority Action | G3: Status
A4: SELF | B4: =C4*D4 -> 80 | C4: 10 | D4: 8 | E4: Sedentary lifestyle, poor sleep, inflammation | F4: Define action | G4: NOT STARTED
A5: FAMILY | B5: =C5*D5 -> 63 | C5: 9 | D5: 7 | E5: Aging parents, genetic risks, chronic conditions | F5: Define action | G5: NOT STARTED
A6: LOCAL | B6: =C6*D6 -> 42 | C6: 7 | D6: 6 | E6: Hospital capacity limits, medical supply chains | F6: Define action | G6: NOT STARTED
A7: NATIONAL | B7: =C7*D7 -> 56 | C7: 8 | D7: 7 | E7: Healthcare system fragility, pandemic response | F7: Define action | G7: NOT STARTED
A8: CIVILIZATIONAL | B8: =C8*D8 -> 48 | C8: 6 | D8: 8 | E8: Antibiotic resistance, bioweapon risk, lab leaks | F8: Define action | G8: NOT STARTED
A9: PLANETARY | B9: =C9*D9 -> 45 | C9: 5 | D9: 9 | E9: Ecosystem collapse, zoonotic spillover, mass extinction | F9: Define action | G9: NOT STARTED
A11: AFFAIRS (DEFENSE) - Hedge tail risks at this scale
A12: Scale | B12: Affair | C12: Stakes | D12: Time (hrs) | E12: Due Date | F12: Status | G12: Completion %
A13: Self
A14: Family
A15: Local
A16: National
A17: Civilizational
A18: Planetary
A20: INTERESTS (OFFENSE) - Asymmetric bets at this scale
A21: Scale | B21: Interest | C21: Asymmetry | D21: Upside | E21: Downside | F21: Status | G21: ROI
A22: Self
A23: Family
A24: Local
A25: National
A26: Civilizational
A27: Planetary
A30: STRATEGIC MATRIX (Overt/Covert × Ally/Enemy × Offense/Defense)
B31: ALLIES OFFENSE | C31: ALLIES DEFENSE | D31: ENEMIES OFFENSE | E31: ENEMIES DEFENSE
A32: OVERT | B32: Define strategy | C32: Define strategy | D32: Define strategy | E32: Define strategy
A33: COVERT | B33: Define strategy | C33: Define strategy | D33: Define strategy | E33: Define strategy

Sheet Ecology
A1: ECOLOGY - Law of Jungle - Dominance hierarchy, predation, Moloch
A3: Scale | B3: Fragility (0-100) | C3: Stakes (1-10) | D3: Risk (1-10) | E3: Vulnerabilities | F3: Priority Action | G3: Status
A4: SELF | B4: =C4*D4 -> 80 | C4: 10 | D4: 8 | E4: Low status, visible wealth, no force capability | F4: Define action | G4: NOT STARTED
A5: FAMILY | B5: =C5*D5 -> 63 | C5: 9 | D5: 7 | E5: Lack of tribe, no protection network | F5: Define action | G5: NOT STARTED
A6: LOCAL | B6: =C6*D6 -> 42 | C6: 7 | D6: 6 | E6: Crime rates, social breakdown, gang activity | F6: Define action | G6: NOT STARTED
A7: NATIONAL | B7: =C7*D7 -> 56 | C7: 8 | D7: 7 | E7: Class warfare, wealth confiscation, mob rule | F7: Define action | G7: NOT STARTED
A8: CIVILIZATIONAL | B8: =C8*D8 -> 48 | C8: 6 | D8: 8 | E8: Moloch dynamics, race to bottom, coordination failure | F8: Define action | G8: NOT STARTED
A9: PLANETARY | B9: =C9*D9 -> 45 | C9: 5 | D9: 9 | E9: Resource wars, geopolitical competition, great filter | F9: Define action | G9: NOT STARTED
A11: AFFAIRS (DEFENSE) - Hedge tail risks at this scale
A12: Scale | B12: Affair | C12: Stakes | D12: Time (hrs) | E12: Due Date | F12: Status | G12: Completion %
A13: Self
A14: Family
A15: Local
A16: National
A17: Civilizational
A18: Planetary
A20: INTERESTS (OFFENSE) - Asymmetric bets at this scale
A21: Scale | B21: Interest | C21: Asymmetry | D21: Upside | E21: Downside | F21: Status | G21: ROI
A22: Self
A23: Family
A24: Local
A25: National
A26: Civilizational
A27: Planetary
A30: STRATEGIC MATRIX (Overt/Covert × Ally/Enemy × Offense/Defense)
B31: ALLIES OFFENSE | C31: ALLIES DEFENSE | D31: ENEMIES OFFENSE | E31: ENEMIES DEFENSE
A32: OVERT | B32: Define strategy | C32: Define strategy | D32: Define strategy | E32: Define strategy
A33: COVERT | B33: Define strategy | C33: Define strategy | D33: Define strategy | E33: Define strategy

Sheet Politics
A1: POLITICS - Law of the Land - Violence, legislation, lawfare
A3: Scale | B3: Fragility (0-100) | C3: Stakes (1-10) | D3: Risk (1-10) | E3: Vulnerabilities | F3: Priority Action | G3: Status
A4: SELF | B4: =C4*D4 -> 80 | C4: 10 | D4: 8 | E4: Traceable assets, legal exposure, single jurisdiction | F4: Define action | G4: NOT STARTED
A5: FAMILY | B5: =C5*D5 -> 63 | C5: 9 | D5: 7 | E5: No dual citizenship, asset concentration | F5: Define action | G5: NOT STARTED
A6: LOCAL | B6: =C6*D6 -> 42 | C6: 7 | D6: 6 | E6: Regulatory capture, local corruption | F6: Define action | G6: NOT STARTED
A7: NATIONAL | B7: =C7*D7 -> 56 | C7: 8 | D7: 7 | E7: Authoritarian drift, asset seizure risk, capital controls | F7: Define action | G7: NOT STARTED
A8: CIVILIZATIONAL | B8: =C8*D8 -> 48 | C8: 6 | D8: 8 | E8: Democracy failure, totalitarian convergence | F8: Define action | G8: NOT STARTED
A9: PLANETARY | B9: =C9*D9 -> 45 | C9: 5 | D9: 9 | E9: One world government risk, global surveillance state | F9: Define action | G9: NOT STARTED
A11: AFFAIRS (DEFENSE) - Hedge tail risks at this scale
A12: Scale | B12: Affair | C12: Stakes | D12: Time (hrs) | E12: Due Date | F12: Status | G12: Completion %
A13: Self
A14: Family
A15: Local
A16: National
A17: Civilizational
A18: Planetary
A20: INTERESTS (OFFENSE) - Asymmetric bets at this scale
A21: Scale | B21: Interest | C21: Asymmetry | D21: Upside | E21: Downside | F21: Status | G21: ROI
A22: Self
A23: Family
A24: Local
A25: National
A26: Civilizational
A27: Planetary
A30: STRATEGIC MATRIX (Overt/Covert × Ally/Enemy × Offense/Defense)
B31: ALLIES OFFENSE | C31: ALLIES DEFENSE | D31: ENEMIES OFFENSE | E31: ENEMIES DEFENSE
A32: OVERT | B32: Define strategy | C32: Define strategy | D32: Define strategy | E32: Define strategy
A33: COVERT | B33: Define strategy | C33: Define strategy | D33: Define strategy | E33: Define strategy

Sheet Finance
A1: FINANCE - Law of Time - Debt, currency collapse, economic entropy
A3: Scale | B3: Fragility (0-100) | C3: Stakes (1-10) | D3: Risk (1-10) | E3: Vulnerabilities | F3: Priority Action | G3: Status
A4: SELF | B4: =C4*D4 -> 80 | C4: 10 | D4: 8 | E4: Debt burden, fiat savings, W2 income only | F4: Define action | G4: NOT STARTED
A5: FAMILY | B5: =C5*D5 -> 63 | C5: 9 | D5: 7 | E5: Single income stream, no generational wealth | F5: Define action | G5: NOT STARTED
A6: LOCAL | B6: =C6*D6 -> 42 | C6: 7 | D6: 6 | E6: Municipal debt, pension crisis, tax base erosion | F6: Define action | G6: NOT STARTED
A7: NATIONAL | B7: =C7*D7 -> 56 | C7: 8 | D7: 7 | E7: Sovereign debt crisis, currency debasement, banking fragility | F7: Define action | G7: NOT STARTED
A8: CIVILIZATIONAL | B8: =C8*D8 -> 48 | C8: 6 | D8: 8 | E8: Fiat endgame, reserve currency collapse, credit bubble | F8: Define action | G8: NOT STARTED
A9: PLANETARY | B9: =C9*D9 -> 45 | C9: 5 | D9: 9 | E9: Global debt saturation, monetary system reset | F9: Define action | G9: NOT STARTED
A11: AFFAIRS (DEFENSE) - Hedge tail risks at this scale
A12: Scale | B12: Affair | C12: Stakes | D12: Time (hrs) | E12: Due Date | F12: Status | G12: Completion %
A13: Self
A14: Family
A15: Local
A16: National
A17: Civilizational
A18: Planetary
A20: INTERESTS (OFFENSE) - Asymmetric bets at this scale
A21: Scale | B21: Interest | C21: Asymmetry | D21: Upside | E21: Downside | F21: Status | G21: ROI
A22: Self
A23: Family
A24: Local
A25: National
A26: Civilizational
A27: Planetary
A30: STRATEGIC MATRIX (Overt/Covert × Ally/Enemy × Offense/Defense)
B31: ALLIES OFFENSE | C31: ALLIES DEFENSE | D31: ENEMIES OFFENSE | E31: ENEMIES DEFENSE
A32: OVERT | B32: Define strategy | C32: Define strategy | D32: Define strategy | E32: Define strategy
A33: COVERT | B33: Define strategy | C33: Define strategy | D33: Define strategy | E33: Define strategy

Sheet Nurture
A1: NURTURE - Laws of Nurture - Culture, rhetoric, madness of crowds
A3: Scale | B3: Fragility (0-100) | C3: Stakes (1-10) | D3: Risk (1-10) | E3: Vulnerabilities | F3: Priority Action | G3: Status
A4: SELF | B4: =C4*D4 -> 80 | C4: 10 | D4: 8 | E4: Reputation risk, cancel culture, mimetic contagion | F4: Define action | G4: NOT STARTED
A5: FAMILY | B5: =C5*D5 -> 63 | C5: 9 | D5: 7 | E5: Social pressure, conformity demands, scapegoating | F5: Define action | G5: NOT STARTED
A6: LOCAL | B6: =C6*D6 -> 42 | C6: 7 | D6: 6 | E6: Mob dynamics, moral panics, witch hunts | F6: Define action | G6: NOT STARTED
A7: NATIONAL | B7: =C7*D7 -> 56 | C7: 8 | D7: 7 | E7: Ideological extremism, culture wars, mass delusion | F7: Define action | G7: NOT STARTED
A8: CIVILIZATIONAL | B8: =C8*D8 -> 48 | C8: 6 | D8: 8 | E8: Information warfare, narrative control, psyops | F8: Define action | G8: NOT STARTED
A9: PLANETARY | B9: =C9*D9 -> 45 | C9: 5 | D9: 9 | E9: Global groupthink, manufactured consensus | F9: Define action | G9: NOT STARTED
A11: AFFAIRS (DEFENSE) - Hedge tail risks at this scale
A12: Scale | B12: Affair | C12: Stakes | D12: Time (hrs) | E12: Due Date | F12: Status | G12: Completion %
A13: Self
A14: Family
A15: Local
A16: National
A17: Civilizational
A18: Planetary
A20: INTERESTS (OFFENSE) - Asymmetric bets at this scale
A21: Scale | B21: Interest | C21: Asymmetry | D21: Upside | E21: Downside | F21: Status | G21: ROI
A22: Self
A23: Family
A24: Local
A25: National
A26: Civilizational
A27: Planetary
A30: STRATEGIC MATRIX (Overt/Covert × Ally/Enemy × Offense/Defense)
B31: ALLIES OFFENSE | C31: ALLIES DEFENSE | D31: ENEMIES OFFENSE | E31: ENEMIES DEFENSE
A32: OVERT | B32: Define strategy | C32: Define strategy | D32: Define strategy | E32: Define strategy
A33: COVERT | B33: Define strategy | C33: Define strategy | D33: Define strategy | E33: Define strategy

Sheet BarbellTracker
A1: BARBELL STRATEGY TRACKER (90/10 DEFENSE/OFFENSE)
A2: Metric | B2: Target | C2: Current | D2: Variance | E2: Status
A3: Affairs % (Defense) | B3: 90 | C3: 85 | D3: =C3-B3 -> -5 | E3: =IF(ABS(D3)<=5,"✓","⚠") -> ✓
A4: Interests % (Offense) | B4: 10 | C4: 15 | D4: =C4-B4 -> 5 | E4: =IF(ABS(D4)<=5,"✓","⚠") -> ✓
A5: Time Allocated (hrs/week) | B5: 150 | C5: 145 | D5: =C5-B5 -> -5 | E5: =IF(ABS(D5)<=10,"✓","⚠") -> ✓
A7: DETAILED BREAKDOWN
A8: Category | B8: Type | C8: Hours/Week | D8: % of Total | E8: Target %
A9: Physics Affairs | B9: Defense | C9: 25 | D9: =C9/168 -> 0.14880952 | E9: 15
A10: Biology Affairs | B10: Defense | C10: 20 | D10: =C10/168 -> 0.11904762 | E10: 12
A11: Finance Affairs | B11: Defense | C11: 30 | D11: =C11/168 -> 0.17857143 | E11: 18
A12: Politics Affairs | B12: Defense | C12: 15 | D12: =C12/168 -> 0.089285714 | E12: 9
A13: Finance Interests | B13: Offense | C13: 10 | D13: =C13/168 -> 0.05952381 | E13: 6
A14: Nurture Interests | B14: Offense | C14: 7 | D14: =C14/168 -> 0.041666667 | E14: 4

Sheet FragilistaTracker
A1: FRAGILISTA TRACKER - People/Institutions Making Asymmetric Bets Against Themselves
A2: Purpose: Identify those with no skin in the game, privatizing gains & socializing losses
A4: Name/Institution | B4: Domain | C4: Stated Preference | D4: Revealed Preference | E4: SITG Score (1-10) | F4: Fragility | G4: Short Position | H4: Confidence | I4: Status | J4: Notes
A5: Jerome Powell | B5: Finance | C5: Inflation is transitory | D5: Continues QE | E5: 2 | F5: HIGH | G5: Long TLT puts | H5: 8 | I5: TRACKING | J5: Fed chair
A6: Local Bank CEO | B6: Finance | C6: Conservative lending | D6: Massive leverage | E6: 3 | F6: HIGH | G6: None yet | H6: 6 | I6: WATCHING
A7: Politician X | B7: Politics | C7: Fiscal responsibility | D7: Votes for spending | E7: 1 | F7: CRITICAL | G7: None | H7: 5 | I7: TRACKING

Sheet WarGaming
A1: WAR GAMING ENGINE - Scenario Planning with Taleb Math
A2: Think in: Ergodicity, Jensen's Inequality, Convexity Effects, Winning vs Being Right
A4: SCENARIO LIBRARY
A5: Scenario | B5: Probability | C5: Impact (1-10) | D5: Ergodic? | E5: Your Exposure | F5: Hedge Status | G5: Convexity | H5: Action Plan
A6: Grid Collapse (CME) | B6: 10% per decade | C6: 10 | D6: NO | E6: HIGH | F6: IN PROGRESS | G6: CONCAVE | H6: Build Faraday cage, stockpile
A7: Financial Crisis | B7: 20% per decade | C7: 9 | D7: NO | E7: MEDIUM | F7: PARTIAL | G7: BARBELL | H7: Gold hedge, clear debt
A8: Pandemic | B8: 5% per decade | C8: 8 | D8: NO | E8: MEDIUM | F8: NOT STARTED | G8: CONCAVE | H8: Rural retreat, supplies
A9: Asset Seizure | B9: 15% per year | C9: 7 | D9: YES | E9: HIGH | F9: NOT STARTED | G9: CONCAVE | H9: Offshore trusts
A10: Currency Collapse | B10: 30% per decade | C10: 10 | D10: NO | E10: HIGH | F10: PARTIAL | G10: BARBELL | H10: Bitcoin, gold, skills
A12: PREPARATION MATRIX
A13: Scenario | B13: Resource Needed | C13: Quantity | D13: Current Stock | E13: Gap | F13: Priority | G13: Budget | H13: Timeline
A14: Grid Collapse | B14: Faraday cages | C14: 2 | D14: 0 | E14: =D14-C14 -> -2 | F14: CRITICAL | G14: $500 | H14: 2 weeks
A15: Grid Collapse | B15: Food (days) | C15: 730 | D15: 0 | E15: =D15-C15 -> -730 | F15: HIGH | G15: $3000 | H15: 3 months
A16: Financial Crisis | B16: Gold (oz) | C16: 50 | D16: 5 | E16: =D16-C16 -> -45 | F16: HIGH | G16: $100k | H16: 6 months
A17: Pandemic | B17: N95 masks | C17: 100 | D17: 0 | E17: =D17-C17 -> -100 | F17: MEDIUM | G17: $50 | H17: 1 week
A18: Asset Seizure | B18: Offshore accounts | C18: 2 | D18: 0 | E18: =D18-C18 -> -2 | F18: HIGH | G18: $5k | H18: 2 months

Sheet StrategicMatrix
A1: STRATEGIC MATRIX - Overt/Covert × Ally/Enemy × Offense/Defense
A2: Selected Domain: | B2: Physics
B4: ALLIES OFFENSE | C4: ALLIES DEFENSE | D4: ENEMIES OFFENSE | E4: ENEMIES DEFENSE
A5: OVERT | B5: Define strategy | C5: Define strategy | D5: Define strategy | E5: Define strategy
A6: COVERT | B6: Define strategy | C6: Define strategy | D6: Define strategy | E6: Define strategy
